Binary Adder/R11590613.v
// starter.v (Rename to <RNumber>.v
//
//  Implement an 8-bit ripple-carry adder.
//
module top(Cin, A, B, Cout, S);

// Verilog code goes here.
    input Cin;
    input[7:0] A;
    input[7:0] B;
    output[7:0] S;
    output Cout;

endmodule

module adder8Bit(Cin, A, B, Cout, S);

    input Cin;
    input[7:0] A,B;
    output Cout;
    output[7:0] S;
    wire[6:0] W;

    

endmodule


module adder4Bit(Cin, A, B, Cout, S);
    input Cin; 
    input[3:0] A;
    input[3:0] B;
    wire[2:0] C;
    output Cout;
    output[3:0] S;

    fullAdder U0 (.Cin(Cin), .A(A[0]), .B(B[0]), .Cout(C[0]), .S(S[0]));
    fullAdder U1 (.Cin(C[0]), .A(A[1]), .B(B[1]), .Cout(C[1]), .S(S[1]));
    fullAdder U2 (.Cin(C[1]), .A(A[2]), .B(B[2]), .Cout(C[2]), .S(S[2]));
    fullAdder U3 (.Cin(C[2]), .A(A[3]), .B(B[3]), .Cout(Cout), .S(S[3]));

endmodule

// Additional modules go here (if necessary).

module fullAdder(Cin, A, B, Cout, S);

    input Cin, A, B;
    output Cout, S;
    
    assign S = Cin ^ A ^ B;
    assign Cout = A&B | Cin&(A^B);

endmodule

Binary Adder/fullAdder_tb.v
`timescale 1ns/1ns
`include "R11590613.v"

module fullAdder_tb();

    reg A,B,Cin;
    wire Cout, S;

    fullAdder UUT(Cin, A, B, Cout, S);
    initial begin
        $dumpfile("fullAdder_tb.vcd");
        $dumpvars(0, fullAdder_tb);

        {Cin, A, B} = 3'd0; #20;
        {Cin, A, B} = 3'd1; #20;
        {Cin, A, B} = 3'd2; #20;
        {Cin, A, B} = 3'd3; #20;
        {Cin, A, B} = 3'd4; #20;
        {Cin, A, B} = 3'd5; #20;
        {Cin, A, B} = 3'd6; #20;
        {Cin, A, B} = 3'd7; #20;

        $display("Test over.");
        

    end

endmodule

Binary Adder/fullAdder_tb.vcd
$date
	Mon Apr 13 17:59:36 2020
$end
$version
	Icarus Verilog
$end
$timescale
	1ns
$end
$scope module fullAdder_tb $end
$var wire 1 ! S $end
$var wire 1 " Cout $end
$var reg 1 # A $end
$var reg 1 $ B $end
$var reg 1 % Cin $end
$scope module UUT $end
$var wire 1 # A $end
$var wire 1 $ B $end
$var wire 1 % Cin $end
$var wire 1 " Cout $end
$var wire 1 ! S $end
$upscope $end
$upscope $end
$enddefinitions $end
#0
$dumpvars
0%
0$
0#
0"
0!
$end
#20
1!
1$
#40
1!
1#
0$
#60
1"
0!
1$
#80
0"
1!
1%
0#
0$
#100
1"
0!
1$
#120
0!
1#
0$
#140
1!
1$
