Simple Combinational Logic/greater_than.v
module greater_than(A,B,F);

input[1:0] A,B;  //Since we want a two bit number. If we needed an 8 bit number: input[7:0]
output F;

//assign F = A > B; - This would technically work. 

assign F = (A[1] & ~B[1]) | (A[0] & ~B[1] & ~B[0]) | (A[1] & A[0] & ~B[0]);


endmodule

Simple Combinational Logic/greater_than_tb.v
`timescale 1ns/1ns
`include "greater_than.v"

module greater_than_tb();

reg [1:0] A,B;
wire F;

greater_than uut(A,B,F);

initial begin
    $dumpfile("greater_than.vcd");
    $dumpvars(0,greater_than_tb);
    {A,B} = 4'd0; #20; //Vector notation 
    {A,B} = 4'd1; #20; //Vector notation 
    {A,B} = 4'd2; #20; //Vector notation 
    {A,B} = 4'd3; #20; //Vector notation 
    {A,B} = 4'd4; #20; //Vector notation 
    {A,B} = 4'd5; #20; //Vector notation 
    {A,B} = 4'd6; #20; //Vector notation 
    {A,B} = 4'd7; #20; //Vector notation 
    {A,B} = 4'd8; #20; //Vector notation 
    {A,B} = 4'd9; #20; //Vector notation 
    {A,B} = 4'd10; #20; //Vector notation 
    {A,B} = 4'd11; #20; //Vector notation 
    {A,B} = 4'd12; #20; //Vector notation 
    {A,B} = 4'd13; #20; //Vector notation 
    {A,B} = 4'd14; #20; //Vector notation 
    {A,B} = 4'd15; #20; //Vector notation 

end

endmodule

Simple Combinational Logic/greater_than.vcd
$date
	Sun Apr  5 04:47:03 2020
$end
$version
	Icarus Verilog
$end
$timescale
	1ns
$end
$scope module greater_than_tb $end
$var wire 1 ! F $end
$var reg 2 " A [1:0] $end
$var reg 2 # B [1:0] $end
$scope module uut $end
$var wire 2 $ A [1:0] $end
$var wire 2 % B [1:0] $end
$var wire 1 ! F $end
$upscope $end
$upscope $end
$enddefinitions $end
#0
$dumpvars
b0 %
b0 $
b0 #
b0 "
0!
$end
#20
b1 #
b1 %
#40
b10 #
b10 %
#60
b11 #
b11 %
#80
1!
b1 "
b1 $
b0 #
b0 %
#100
0!
b1 #
b1 %
#120
0!
b10 #
b10 %
#140
b11 #
b11 %
#160
1!
b10 "
b10 $
b0 #
b0 %
#180
b1 #
b1 %
#200
0!
b10 #
b10 %
#220
b11 #
b11 %
#240
1!
b11 "
b11 $
b0 #
b0 %
#260
b1 #
b1 %
#280
b10 #
b10 %
#300
0!
b11 #
b11 %
