multiplexer/mux32to1.v
module mux32to1(S,I,Y);

    input[4:0] S; //Switch signals
    input[31:0] I; //Input signals
    wire[31:0] W; //Wires for the Decoder output
    wire[31:0] E; //Wires for the Enabler Gate
    output Y; //Final output

    decoder5to32 U0(.A(S[4:0]), .D(W[31:0]));
    
    assign E[0] = W[0] & I[0];
    assign E[1] = W[1] & I[1];
    assign E[2] = W[2] & I[2];
    assign E[3] = W[3] & I[3];
    assign E[4] = W[4] & I[4];
    assign E[5] = W[5] & I[5];
    assign E[6] = W[6] & I[6];
    assign E[7] = W[7] & I[7];

    assign E[8] = W[8] & I[8];
    assign E[9] = W[9] & I[9];
    assign E[10] = W[10] & I[10];
    assign E[11] = W[11] & I[11];
    assign E[12] = W[12] & I[12];
    assign E[13] = W[13] & I[13];
    assign E[14] = W[14] & I[14];
    assign E[15] = W[15] & I[15];


    assign E[16] = W[16] & I[16];
    assign E[17] = W[17] & I[17];
    assign E[18] = W[18] & I[18];
    assign E[19] = W[19] & I[19];
    assign E[20] = W[20] & I[20];
    assign E[21] = W[21] & I[21];
    assign E[22] = W[22] & I[22];
    assign E[23] = W[23] & I[23];


    assign E[24] = W[24] & I[24];
    assign E[25] = W[25] & I[25];
    assign E[26] = W[26] & I[26];
    assign E[27] = W[27] & I[27];
    assign E[28] = W[28] & I[28];
    assign E[29] = W[29] & I[29];
    assign E[30] = W[30] & I[30];
    assign E[31] = W[31] & I[31];


    assign Y = E[0] | E[1] | E[2] | E[3] | E[4] | E[5] | E[6] | E[7] |
            E[8] | E[9] | E[10] | E[11] | E[12] | E[13] | E[14] | E[15] |
            E[16] | E[17] | E[18] | E[19] | E[20] | E[21] | E[22] | E[23] |
            E[24] | E[25] | E[26] | E[27] | E[28] | E[29] | E[30] | E[31] ;

endmodule


module decoder5to32(A, D);

    input [4:0] A;
    output[31:0] D;
    wire[11:0] W;

    decoder3to8 U0(.A(A[2:0]),.D(W[11:4]));
    decoder2to4 U1(.A(A[4:3]), .D(W[3:0]));

    assign D[0] = W[4] & W[0];
    assign D[1] = W[5] & W[0];
    assign D[2] = W[6] & W[0];
    assign D[3] = W[7] & W[0];
    assign D[4] = W[8] & W[0];
    assign D[5] = W[9] & W[0];
    assign D[6] = W[10] & W[0];
    assign D[7] = W[11] & W[0];

    assign D[8] = W[4] & W[1];
    assign D[9] = W[5] & W[1];
    assign D[10] = W[6] & W[1];
    assign D[11] = W[7] & W[1];
    assign D[12] = W[8] & W[1];
    assign D[13] = W[9] & W[1];
    assign D[14] = W[10] & W[1];
    assign D[15] = W[11] & W[1];

    assign D[16] = W[4] & W[2];
    assign D[17] = W[5] & W[2];
    assign D[18] = W[6] & W[2];
    assign D[19] = W[7] & W[2];
    assign D[20] = W[8] & W[2];
    assign D[21] = W[9] & W[2];
    assign D[22] = W[10] & W[2];
    assign D[23] = W[11] & W[2];

    assign D[24] = W[4] & W[3];
    assign D[25] = W[5] & W[3];
    assign D[26] = W[6] & W[3];
    assign D[27] = W[7] & W[3];
    assign D[28] = W[8] & W[3];
    assign D[29] = W[9] & W[3];
    assign D[30] = W[10] & W[3];
    assign D[31] = W[11] & W[3];



endmodule

// OTHER MODULES HERE (IF REQUIRED)

module decoder1to2(A,D);

    input A;
    output[1:0] D;

    assign D[0] = ~A;
    assign D[1] = A;

endmodule

module decoder2to4(A,D);

    input[1:0] A;
    output[3:0] D;

    wire[3:0] W;

    decoder1to2 U0(.A(A[0]),.D(W[3:2]));
    decoder1to2 U1(.A(A[1]),.D(W[1:0]));

    assign D[0] = W[3] & W[1];  
    assign D[1] = W[2] & W[1];
    assign D[2] = W[3] & W[0];
    assign D[3] = W[2] & W[0];

endmodule

module decoder3to8(A,D);

    input[2:0] A;
    output[7:0] D;

    wire[5:0] W;

    decoder2to4 U0(.A(A[1:0]), .D(W[5:2]));
    decoder1to2 U1(.A(A[2]), .D(W[1:0]));

    assign D[0] = W[2] & W[1];
    assign D[1] = W[3] & W[1];
    assign D[2] = W[4] & W[1];
    assign D[3] = W[5] & W[1];
    assign D[4] = W[2] & W[0];
    assign D[5] = W[3] & W[0];
    assign D[6] = W[4] & W[0]; 
    assign D[7] = W[5] & W[0];


endmodule

multiplexer/decoder5to32_tb.v
`timescale 1ns/1ns
`include "mux32to1.v"

module decoder5to32_tb();

    reg[4:0] A;
    wire[31:0] D;

    decoder5to32 UUT(A,D);
    
    initial begin
        $dumpfile("decoder5to32_tb.vcd");
        $dumpvars(0, decoder5to32_tb);
        A= 5'd00; #15;
        A= 5'd01; #15;
        A= 5'd02; #15;
        A= 5'd03; #15;
        A= 5'd04; #15;
        A= 5'd05; #15;
        A= 5'd06; #15;
        A= 5'd07; #15;
        A= 5'd08; #15;
        A= 5'd09; #15;
        A= 5'd10; #15;
        A= 5'd11; #15;
        A= 5'd12; #15;
        A= 5'd13; #15;
        A= 5'd14; #15;
        A= 5'd15; #15;
        A= 5'd16; #15;
        A= 5'd17; #15;
        A= 5'd18; #15;
        A= 5'd19; #15;
        A= 5'd20; #15;
        A= 5'd21; #15;
        A= 5'd22; #15;
        A= 5'd23; #15;
        A= 5'd24; #15;
        A= 5'd25; #15;
        A= 5'd26; #15;
        A= 5'd27; #15;
        A= 5'd28; #15;
        A= 5'd29; #15; 
        A= 5'd30; #15; 
        A= 5'd31; #15; 

        $display("test done");

    end

endmodule

multiplexer/decoder5to32_tb.vcd
$date
	Thu Apr  9 23:35:03 2020
$end
$version
	Icarus Verilog
$end
$timescale
	1ns
$end
$scope module decoder5to32_tb $end
$var wire 32 ! D [31:0] $end
$var reg 5 " A [4:0] $end
$scope module UUT $end
$var wire 5 # A [4:0] $end
$var wire 12 $ W [11:0] $end
$var wire 32 % D [31:0] $end
$scope module U0 $end
$var wire 3 & A [2:0] $end
$var wire 6 ' W [5:0] $end
$var wire 8 ( D [7:0] $end
$scope module U0 $end
$var wire 2 ) A [1:0] $end
$var wire 4 * W [3:0] $end
$var wire 4 + D [3:0] $end
$scope module U0 $end
$var wire 1 , A $end
$var wire 2 - D [1:0] $end
$upscope $end
$scope module U1 $end
$var wire 1 . A $end
$var wire 2 / D [1:0] $end
$upscope $end
$upscope $end
$scope module U1 $end
$var wire 1 0 A $end
$var wire 2 1 D [1:0] $end
$upscope $end
$upscope $end
$scope module U1 $end
$var wire 2 2 A [1:0] $end
$var wire 4 3 W [3:0] $end
$var wire 4 4 D [3:0] $end
$scope module U0 $end
$var wire 1 5 A $end
$var wire 2 6 D [1:0] $end
$upscope $end
$scope module U1 $end
$var wire 1 7 A $end
$var wire 2 8 D [1:0] $end
$upscope $end
$upscope $end
$upscope $end
$upscope $end
$enddefinitions $end
#0
$dumpvars
b1 8
07
b1 6
05
b1000 4
b101 3
b0 2
b1 1
00
b1 /
0.
b1 -
0,
b1000 +
b101 *
b0 )
b10000000 (
b100001 '
b0 &
b10000000000000000000000000000000 %
b100000001000 $
b0 #
b0 "
b10000000000000000000000000000000 !
$end
#15
b1000000000000000000000000000000 !
b1000000000000000000000000000000 %
b10000001000 $
b1000000 (
b10001 '
b100 +
b1001 *
b10 -
1,
b1 )
b1 &
b1 "
b1 #
#30
b100000000000000000000000000000 !
b100000000000000000000000000000 %
b1000001000 $
b100000 (
b1001 '
b10 +
b1 -
0,
b110 *
b10 /
1.
b10 )
b10 &
b10 "
b10 #
#45
b10000000000000000000000000000 !
b10000000000000000000000000000 %
b100001000 $
b10000 (
b101 '
b1 +
b1010 *
b10 -
1,
b11 )
b11 &
b11 "
b11 #
#60
b1000000000000000000000000000 !
b1000000000000000000000000000 %
b1000 +
b10001000 $
b1000 (
b1 -
0,
b101 *
b1 /
0.
b0 )
b100010 '
b10 1
10
b100 &
b100 "
b100 #
#75
b100000000000000000000000000 !
b100000000000000000000000000 %
b1001000 $
b100 (
b10010 '
b100 +
b1001 *
b10 -
1,
b1 )
b101 &
b101 "
b101 #
#90
b10000000000000000000000000 !
b10000000000000000000000000 %
b101000 $
b10 (
b1010 '
b10 +
b1 -
0,
b110 *
b10 /
1.
b10 )
b110 &
b110 "
b110 #
#105
b1000000000000000000000000 !
b1000000000000000000000000 %
b11000 $
b1 (
b110 '
b1 +
b1010 *
b10 -
1,
b11 )
b111 &
b111 "
b111 #
#120
b100000000000000000000000 !
b100000000000000000000000 %
b1000 +
b10000000 (
b100000000100 $
b100 4
b1 -
0,
b101 *
b1 /
0.
b0 )
b100001 '
b1 1
00
b1001 3
b10 6
15
b0 &
b1 2
b1000 "
b1000 #
#135
b10000000000000000000000 !
b10000000000000000000000 %
b10000000100 $
b1000000 (
b10001 '
b100 +
b1001 *
b10 -
1,
b1 )
b1 &
b1001 "
b1001 #
#150
b1000000000000000000000 !
b1000000000000000000000 %
b1000000100 $
b100000 (
b1001 '
b10 +
b1 -
0,
b110 *
b10 /
1.
b10 )
b10 &
b1010 "
b1010 #
#165
b100000000000000000000 !
b100000000000000000000 %
b100000100 $
b10000 (
b101 '
b1 +
b1010 *
b10 -
1,
b11 )
b11 &
b1011 "
b1011 #
#180
b10000000000000000000 !
b10000000000000000000 %
b1000 +
b10000100 $
b1000 (
b1 -
0,
b101 *
b1 /
0.
b0 )
b100010 '
b10 1
10
b100 &
b1100 "
b1100 #
#195
b1000000000000000000 !
b1000000000000000000 %
b1000100 $
b100 (
b10010 '
b100 +
b1001 *
b10 -
1,
b1 )
b101 &
b1101 "
b1101 #
#210
b100000000000000000 !
b100000000000000000 %
b100100 $
b10 (
b1010 '
b10 +
b1 -
0,
b110 *
b10 /
1.
b10 )
b110 &
b1110 "
b1110 #
#225
b10000000000000000 !
b10000000000000000 %
b10100 $
b1 (
b110 '
b1 +
b1010 *
b10 -
1,
b11 )
b111 &
b1111 "
b1111 #
#240
b1000000000000000 !
b1000000000000000 %
b1000 +
b10000000 (
b100000000010 $
b10 4
b1 -
0,
b101 *
b1 /
0.
b0 )
b100001 '
b1 1
00
b1 6
05
b110 3
b10 8
17
b0 &
b10 2
b10000 "
b10000 #
#255
b100000000000000 !
b100000000000000 %
b10000000010 $
b1000000 (
b10001 '
b100 +
b1001 *
b10 -
1,
b1 )
b1 &
b10001 "
b10001 #
#270
b10000000000000 !
b10000000000000 %
b1000000010 $
b100000 (
b1001 '
b10 +
b1 -
0,
b110 *
b10 /
1.
b10 )
b10 &
b10010 "
b10010 #
#285
b1000000000000 !
b1000000000000 %
b100000010 $
b10000 (
b101 '
b1 +
b1010 *
b10 -
1,
b11 )
b11 &
b10011 "
b10011 #
#300
b100000000000 !
b100000000000 %
b1000 +
b10000010 $
b1000 (
b1 -
0,
b101 *
b1 /
0.
b0 )
b100010 '
b10 1
10
b100 &
b10100 "
b10100 #
#315
b10000000000 !
b10000000000 %
b1000010 $
b100 (
b10010 '
b100 +
b1001 *
b10 -
1,
b1 )
b101 &
b10101 "
b10101 #
#330
b1000000000 !
b1000000000 %
b100010 $
b10 (
b1010 '
b10 +
b1 -
0,
b110 *
b10 /
1.
b10 )
b110 &
b10110 "
b10110 #
#345
b100000000 !
b100000000 %
b10010 $
b1 (
b110 '
b1 +
b1010 *
b10 -
1,
b11 )
b111 &
b10111 "
b10111 #
#360
b10000000 !
b10000000 %
b1000 +
b10000000 (
b100000000001 $
b1 4
b1 -
0,
b101 *
b1 /
0.
b0 )
b100001 '
b1 1
00
b1010 3
b10 6
15
b0 &
b11 2
b11000 "
b11000 #
#375
b1000000 !
b1000000 %
b10000000001 $
b1000000 (
b10001 '
b100 +
b1001 *
b10 -
1,
b1 )
b1 &
b11001 "
b11001 #
#390
b100000 !
b100000 %
b1000000001 $
b100000 (
b1001 '
b10 +
b1 -
0,
b110 *
b10 /
1.
b10 )
b10 &
b11010 "
b11010 #
#405
b10000 !
b10000 %
b100000001 $
b10000 (
b101 '
b1 +
b1010 *
b10 -
1,
b11 )
b11 &
b11011 "
b11011 #
#420
b1000 !
b1000 %
b1000 +
b10000001 $
b1000 (
b1 -
0,
b101 *
b1 /
0.
b0 )
b100010 '
b10 1
10
b100 &
b11100 "
b11100 #
#435
b100 !
b100 %
b1000001 $
b100 (
b10010 '
b100 +
b1001 *
b10 -
1,
b1 )
b101 &
b11101 "
b11101 #
#450
b10 !
b10 %
b100001 $
b10 (
b1010 '
b10 +
b1 -
0,
b110 *
b10 /
1.
b10 )
b110 &
b11110 "
b11110 #
#465
b1 !
b1 %
b10001 $
b1 (
b110 '
b1 +
b1010 *
b10 -
1,
b11 )
b111 &
b11111 "
b11111 #
