multiplexer/mux32to1.v
module mux32to1(S,I,Y);

    input[4:0] S; //Switch signals
    input[31:0] I; //Input signals
    wire[31:0] W; //Wires for the Decoder output
    wire[31:0] E; //Wires for the Enabler Gate
    output Y; //Final output

    decoder5to32 U0(.A(S[4:0]), .D(W[31:0]));
    
    assign E[0] = W[0] & I[0];
    assign E[1] = W[1] & I[1];
    assign E[2] = W[2] & I[2];
    assign E[3] = W[3] & I[3];
    assign E[4] = W[4] & I[4];
    assign E[5] = W[5] & I[5];
    assign E[6] = W[6] & I[6];
    assign E[7] = W[7] & I[7];

    assign E[8] = W[8] & I[8];
    assign E[9] = W[9] & I[9];
    assign E[10] = W[10] & I[10];
    assign E[11] = W[11] & I[11];
    assign E[12] = W[12] & I[12];
    assign E[13] = W[13] & I[13];
    assign E[14] = W[14] & I[14];
    assign E[15] = W[15] & I[15];


    assign E[16] = W[16] & I[16];
    assign E[17] = W[17] & I[17];
    assign E[18] = W[18] & I[18];
    assign E[19] = W[19] & I[19];
    assign E[20] = W[20] & I[20];
    assign E[21] = W[21] & I[21];
    assign E[22] = W[22] & I[22];
    assign E[23] = W[23] & I[23];


    assign E[24] = W[24] & I[24];
    assign E[25] = W[25] & I[25];
    assign E[26] = W[26] & I[26];
    assign E[27] = W[27] & I[27];
    assign E[28] = W[28] & I[28];
    assign E[29] = W[29] & I[29];
    assign E[30] = W[30] & I[30];
    assign E[31] = W[31] & I[31];


    assign Y = E[0] | E[1] | E[2] | E[3] | E[4] | E[5] | E[6] | E[7] |
            E[8] | E[9] | E[10] | E[11] | E[12] | E[13] | E[14] | E[15] |
            E[16] | E[17] | E[18] | E[19] | E[20] | E[21] | E[22] | E[23] |
            E[24] | E[25] | E[26] | E[27] | E[28] | E[29] | E[30] | E[31] ;

endmodule


module decoder5to32(A, D);

    input [4:0] A;
    output[31:0] D;
    wire[11:0] W;

    decoder3to8 U0(.A(A[2:0]),.D(W[11:4]));
    decoder2to4 U1(.A(A[4:3]), .D(W[3:0]));

    assign D[0] = W[4] & W[0];
    assign D[1] = W[5] & W[0];
    assign D[2] = W[6] & W[0];
    assign D[3] = W[7] & W[0];
    assign D[4] = W[8] & W[0];
    assign D[5] = W[9] & W[0];
    assign D[6] = W[10] & W[0];
    assign D[7] = W[11] & W[0];

    assign D[8] = W[4] & W[1];
    assign D[9] = W[5] & W[1];
    assign D[10] = W[6] & W[1];
    assign D[11] = W[7] & W[1];
    assign D[12] = W[8] & W[1];
    assign D[13] = W[9] & W[1];
    assign D[14] = W[10] & W[1];
    assign D[15] = W[11] & W[1];

    assign D[16] = W[4] & W[2];
    assign D[17] = W[5] & W[2];
    assign D[18] = W[6] & W[2];
    assign D[19] = W[7] & W[2];
    assign D[20] = W[8] & W[2];
    assign D[21] = W[9] & W[2];
    assign D[22] = W[10] & W[2];
    assign D[23] = W[11] & W[2];

    assign D[24] = W[4] & W[3];
    assign D[25] = W[5] & W[3];
    assign D[26] = W[6] & W[3];
    assign D[27] = W[7] & W[3];
    assign D[28] = W[8] & W[3];
    assign D[29] = W[9] & W[3];
    assign D[30] = W[10] & W[3];
    assign D[31] = W[11] & W[3];



endmodule

// OTHER MODULES HERE (IF REQUIRED)

module decoder1to2(A,D);

    input A;
    output[1:0] D;

    assign D[0] = ~A;
    assign D[1] = A;

endmodule

module decoder2to4(A,D);

    input[1:0] A;
    output[3:0] D;

    wire[3:0] W;

    decoder1to2 U0(.A(A[0]),.D(W[3:2]));
    decoder1to2 U1(.A(A[1]),.D(W[1:0]));

    assign D[0] = W[3] & W[1];  
    assign D[1] = W[2] & W[1];
    assign D[2] = W[3] & W[0];
    assign D[3] = W[2] & W[0];

endmodule

module decoder3to8(A,D);

    input[2:0] A;
    output[7:0] D;

    wire[5:0] W;

    decoder2to4 U0(.A(A[1:0]), .D(W[5:2]));
    decoder1to2 U1(.A(A[2]), .D(W[1:0]));

    assign D[0] = W[2] & W[1];
    assign D[1] = W[3] & W[1];
    assign D[2] = W[4] & W[1];
    assign D[3] = W[5] & W[1];
    assign D[4] = W[2] & W[0];
    assign D[5] = W[3] & W[0];
    assign D[6] = W[4] & W[0]; 
    assign D[7] = W[5] & W[0];


endmodule

multiplexer/mux32to1_tb.v
`timescale 1ns/1ns
`include "mux32to1.v"

module mux32to1_tb();

    reg[4:0] S;
    reg[31:0] I;
    wire Y;

    mux32to1 UUT(S,I,Y);

    initial begin
        $dumpfile("mux32to1_tb.vcd");
        $dumpvars(0, mux32to1_tb);

        S = 5'd00; 
        I = 32'd00; #20;

        S = 5'd01; 
        I = 32'd01; #20;

        S = 5'd02; 
        I = 32'd02; #20;

        S = 5'd03; 
        I = 32'd03; #20;

        S = 5'd04; 
        I = 32'd04; #20;

        S = 5'd05; 
        I = 32'd05; #20;

        S = 5'd06; 
        I = 32'd06; #20;

        S = 5'd07; 
        I = 32'd07; #20;

        S = 5'd08; 
        I = 32'd08; #20;

        $display("test ended");
    end


endmodule

multiplexer/mux32to1_tb.vcd
$date
	Fri Apr 10 00:48:21 2020
$end
$version
	Icarus Verilog
$end
$timescale
	1ns
$end
$scope module mux32to1_tb $end
$var wire 1 ! Y $end
$var reg 32 " I [31:0] $end
$var reg 5 # S [4:0] $end
$scope module UUT $end
$var wire 32 $ I [31:0] $end
$var wire 5 % S [4:0] $end
$var wire 1 ! Y $end
$var wire 32 & W [31:0] $end
$var wire 32 ' E [31:0] $end
$scope module U0 $end
$var wire 5 ( A [4:0] $end
$var wire 12 ) W [11:0] $end
$var wire 32 * D [31:0] $end
$scope module U0 $end
$var wire 3 + A [2:0] $end
$var wire 6 , W [5:0] $end
$var wire 8 - D [7:0] $end
$scope module U0 $end
$var wire 2 . A [1:0] $end
$var wire 4 / W [3:0] $end
$var wire 4 0 D [3:0] $end
$scope module U0 $end
$var wire 1 1 A $end
$var wire 2 2 D [1:0] $end
$upscope $end
$scope module U1 $end
$var wire 1 3 A $end
$var wire 2 4 D [1:0] $end
$upscope $end
$upscope $end
$scope module U1 $end
$var wire 1 5 A $end
$var wire 2 6 D [1:0] $end
$upscope $end
$upscope $end
$scope module U1 $end
$var wire 2 7 A [1:0] $end
$var wire 4 8 W [3:0] $end
$var wire 4 9 D [3:0] $end
$scope module U0 $end
$var wire 1 : A $end
$var wire 2 ; D [1:0] $end
$upscope $end
$scope module U1 $end
$var wire 1 < A $end
$var wire 2 = D [1:0] $end
$upscope $end
$upscope $end
$upscope $end
$upscope $end
$upscope $end
$enddefinitions $end
#0
$dumpvars
b1 =
0<
b1 ;
0:
b1000 9
b101 8
b0 7
b1 6
05
b1 4
03
b1 2
01
b1000 0
b101 /
b0 .
b10000000 -
b100001 ,
b0 +
b10000000000000000000000000000000 *
b100000001000 )
b0 (
b0 '
b10000000000000000000000000000000 &
b0 %
b0 $
b0 #
b0 "
0!
$end
#20
b1000000000000000000000000000000 &
b1000000000000000000000000000000 *
b10000001000 )
b1000000 -
b10001 ,
b100 0
b1001 /
b10 2
11
b1 .
b1 +
b1 "
b1 $
b1 #
b1 %
b1 (
#40
b100000000000000000000000000000 &
b100000000000000000000000000000 *
b1000001000 )
b100000 -
b1001 ,
b10 0
b1 2
01
b110 /
b10 4
13
b10 .
b10 +
b10 "
b10 $
b10 #
b10 %
b10 (
#60
b10000000000000000000000000000 &
b10000000000000000000000000000 *
b100001000 )
b10000 -
b101 ,
b1 0
b1010 /
b10 2
11
b11 .
b11 +
b11 "
b11 $
b11 #
b11 %
b11 (
#80
b1000000000000000000000000000 &
b1000000000000000000000000000 *
b1000 0
b10001000 )
b1000 -
b1 2
01
b101 /
b1 4
03
b0 .
b100010 ,
b10 6
15
b100 +
b100 "
b100 $
b100 #
b100 %
b100 (
#100
b100000000000000000000000000 &
b100000000000000000000000000 *
b1001000 )
b100 -
b10010 ,
b100 0
b1001 /
b10 2
11
b1 .
b101 +
b101 "
b101 $
b101 #
b101 %
b101 (
#120
b10000000000000000000000000 &
b10000000000000000000000000 *
b101000 )
b10 -
b1010 ,
b10 0
b1 2
01
b110 /
b10 4
13
b10 .
b110 +
b110 "
b110 $
b110 #
b110 %
b110 (
#140
b1000000000000000000000000 &
b1000000000000000000000000 *
b11000 )
b1 -
b110 ,
b1 0
b1010 /
b10 2
11
b11 .
b111 +
b111 "
b111 $
b111 #
b111 %
b111 (
#160
b100000000000000000000000 &
b100000000000000000000000 *
b1000 0
b10000000 -
b100000000100 )
b100 9
b1 2
01
b101 /
b1 4
03
b0 .
b100001 ,
b1 6
05
b1001 8
b10 ;
1:
b0 +
b1 7
b1000 "
b1000 $
b1000 #
b1000 %
b1000 (
